msgraphbackend/__init__.py
django_msgraphbackend-1.0.0.dist-info/LICENSE
django_msgraphbackend-1.0.0.dist-info/METADATA
django_msgraphbackend-1.0.0.dist-info/WHEEL
django_msgraphbackend-1.0.0.dist-info/top_level.txt
django_msgraphbackend-1.0.0.dist-info/RECORD
