Metadata-Version: 2.1
Name: django-msgraphbackend
Version: 1.0.0
Summary: A Microsoft Graph Email Backend for Django.
Author-email: Daniel Niccoli <daniel.niccoli@gmail.com>
License: MIT License
Project-URL: Homepage, https://github.com/danielniccoli/django-msgraphbackend
Project-URL: Repository, https://github.com/danielniccoli/django-msgraphbackend.git
Project-URL: Issues, https://github.com/danielniccoli/django-msgraphbackend/issues
Keywords: Django,Backend,EmailBackend,Microsoft Graph
Classifier: Framework :: Django
Classifier: Framework :: Django :: 4.2
Classifier: Framework :: Django :: 5.0
Classifier: Programming Language :: Python :: 3.9
Classifier: Programming Language :: Python :: 3.10
Classifier: Programming Language :: Python :: 3.11
Classifier: Programming Language :: Python :: 3.12
Requires-Python: >=3.9
License-File: LICENSE
